README
setup.py
wizard/__init__.py
wizard/deploy.py
wizard/git.py
wizard/merge.py
wizard/old_log.py
wizard/plugin.py
wizard/prompt.py
wizard/report.py
wizard/resolve.py
wizard/shell.py
wizard/sql.py
wizard/sset.py
wizard/user.py
wizard/util.py
wizard.egg-info/PKG-INFO
wizard.egg-info/SOURCES.txt
wizard.egg-info/dependency_links.txt
wizard.egg-info/requires.txt
wizard.egg-info/top_level.txt
wizard/app/__init__.py
wizard/app/mediawiki.py
wizard/app/php.py
wizard/app/phpBB.py
wizard/app/wordpress.py
wizard/command/__init__.py
wizard/command/backup.py
wizard/command/blacklist.py
wizard/command/database.py
wizard/command/errors.py
wizard/command/install.py
wizard/command/list.py
wizard/command/mass_migrate.py
wizard/command/mass_upgrade.py
wizard/command/migrate.py
wizard/command/prepare_config.py
wizard/command/prepare_pristine.py
wizard/command/quota.py
wizard/command/remove.py
wizard/command/research.py
wizard/command/restore.py
wizard/command/upgrade.py
wizard/command/summary/__init__.py
wizard/command/summary/unsupported.py
wizard/command/summary/version.py
wizard/install/__init__.py
wizard/install/installopt.py
wizard/install/interactive.py
wizard/sphinx/__init__.py
wizard/sphinx/supplement.py
wizard/tests/__init__.py
wizard/tests/deploy_test.py
wizard/tests/merge_test.py
wizard/tests/old_log_test.py
wizard/tests/resolve_test.py
wizard/tests/util_test.py