Metadata-Version: 1.0
Name: wizard
Version: 0.1.dev
Summary: A next-generation autoinstall management system
Home-page: http://scripts.mit.edu/wizard
Author: The Wizard Team
Author-email: scripts-team@mit.edu
License: MIT
Keywords: autoinstall webapp deploy
Platform: UNKNOWN
